odoo/addons/website_sale_cart_expire/README.rst
odoo/addons/website_sale_cart_expire/__init__.py
odoo/addons/website_sale_cart_expire/__manifest__.py
odoo/addons/website_sale_cart_expire/data/ir_cron.xml
odoo/addons/website_sale_cart_expire/i18n/ja.po
odoo/addons/website_sale_cart_expire/i18n/website_sale_cart_expire.pot
odoo/addons/website_sale_cart_expire/models/__init__.py
odoo/addons/website_sale_cart_expire/models/res_config_settings.py
odoo/addons/website_sale_cart_expire/models/sale_order.py
odoo/addons/website_sale_cart_expire/models/website.py
odoo/addons/website_sale_cart_expire/readme/CONFIGURE.rst
odoo/addons/website_sale_cart_expire/readme/CONTRIBUTORS.rst
odoo/addons/website_sale_cart_expire/readme/DESCRIPTION.rst
odoo/addons/website_sale_cart_expire/static/description/icon.png
odoo/addons/website_sale_cart_expire/static/description/index.html
odoo/addons/website_sale_cart_expire/tests/__init__.py
odoo/addons/website_sale_cart_expire/tests/test_website_sale_cart_expire.py
odoo/addons/website_sale_cart_expire/views/res_config_settings.xml
odoo13_addon_website_sale_cart_expire-13.0.1.0.1.dev7.dist-info/METADATA
odoo13_addon_website_sale_cart_expire-13.0.1.0.1.dev7.dist-info/WHEEL
odoo13_addon_website_sale_cart_expire-13.0.1.0.1.dev7.dist-info/top_level.txt
odoo13_addon_website_sale_cart_expire-13.0.1.0.1.dev7.dist-info/RECORD
